brokeapi/__init__.py
brokeapi-1.0.1.dist-info/METADATA
brokeapi-1.0.1.dist-info/WHEEL
brokeapi-1.0.1.dist-info/top_level.txt
brokeapi-1.0.1.dist-info/RECORD
