Metadata-Version: 2.4
Name: brokeapi
Version: 1.0.1
Summary: Simple Python client for BrokeAPI chat endpoint
Home-page: https://github.com/rifatgamingop/brokeapi
Author: NotHerXenon
Author-email: rifatarefinchowdhury@gmail.com
Classifier: Programming Language :: Python :: 3
Classifier: Operating System :: OS Independent
Requires-Python: >=3.6
Requires-Dist: requests
Dynamic: author
Dynamic: author-email
Dynamic: classifier
Dynamic: description
Dynamic: description-content-type
Dynamic: home-page
Dynamic: requires-dist
Dynamic: requires-python
Dynamic: summary
